spothinta_api/__init__.py
spothinta_api/const.py
spothinta_api/exceptions.py
spothinta_api/models.py
spothinta_api/py.typed
spothinta_api/spothinta.py
spothinta_api-0.7.2.dist-info/METADATA
spothinta_api-0.7.2.dist-info/WHEEL
spothinta_api-0.7.2.dist-info/entry_points.txt
spothinta_api-0.7.2.dist-info/licenses/LICENSE
spothinta_api-0.7.2.dist-info/RECORD
