Metadata-Version: 2.4
Name: spothinta-api
Version: 0.7.2
Summary: Asynchronous Python client providing energy prices from spot-hinta.fi
License: MIT
License-File: LICENSE
Keywords: energy,spothinta,prices,api,async,client
Author: Sebastian Lövdahl
Author-email: sebastian.lovdahl@hibox.fi
Maintainer: Sebastian Lövdahl
Maintainer-email: sebastian.lovdahl@hibox.fi
Requires-Python: >=3.10,<4.0
Classifier: Framework :: AsyncIO
Classifier: Intended Audience :: Developers
Classifier: License :: OSI Approved :: MIT License
Classifier: Natural Language :: English
Classifier: Programming Language :: Python :: 3
Classifier: Programming Language :: Python :: 3.10
Classifier: Programming Language :: Python :: 3.11
Classifier: Programming Language :: Python :: 3.12
Classifier: Programming Language :: Python :: 3.13
Classifier: Programming Language :: Python :: 3.14
Classifier: Topic :: Software Development :: Libraries :: Python Modules
Requires-Dist: aiohttp (>=3.0.0)
Requires-Dist: aiozoneinfo (==0.*)
Requires-Dist: async-timeout (>=4.0.3,<6.0.0)
Requires-Dist: yarl (>=1.6.0)
